{"hash":"6262819acdaacae2680f9f357fad30363400f996","data":{"markdownPage":{"id":"5c7a69b0ceba4c29b5b0e1b2b0cecf7e","title":"Feature Demo Videos","description":"","path":"/bpm6-intro/example-video/","timeToRead":1,"content":"<h1 id=\"feature-demo-videos\"><a href=\"#feature-demo-videos\" aria-hidden=\"true\"><span class=\"icon icon-link\"></span></a>Feature Demo Videos</h1>\n<br>\n<h3>uEngine6 BPM Demo (Full Version)</h3>\n<div style=\"position: relative; padding-bottom: 56.25%; padding-top: 0px; height: 0; overflow: hidden;\">\n\t<iframe style=\"position: absolute; top: 0; left: 0; width: 100%; height: 100%;\" \n        src=\"https://www.youtube.com/embed/ZmytoLlvpMs\" \n        frameborder=\"0\" crolling=\"no\" frameborder=\"none\" allowfullscreen=\"\">\n    </iframe>\n</div>\n<br><br>\n<h3>Basic BPM Process</h3>\n<div style=\"position: relative; padding-bottom: 56.25%; padding-top: 0px; height: 0; overflow: hidden;\">\n\t<iframe style=\"position: absolute; top: 0; left: 0; width: 100%; height: 100%;\" \n        src=\"https://www.youtube.com/embed/fyoGZStLlVo\" \n        frameborder=\"0\" crolling=\"no\" frameborder=\"none\" allowfullscreen=\"\">\n    </iframe>\n</div>\n<br><br>\n<h3>Subprocess Configuration</h3>\n<div style=\"position: relative; padding-bottom: 56.25%; padding-top: 0px; height: 0; overflow: hidden;\">\n\t<iframe style=\"position: absolute; top: 0; left: 0; width: 100%; height: 100%;\" \n        src=\"https://www.youtube.com/embed/nhQCDfYa6Gk\" \n        frameborder=\"0\" crolling=\"no\" frameborder=\"none\" allowfullscreen=\"\">\n    </iframe>\n</div>\n<br><br>\n<h3>Conditional Branching</h3>\n<div style=\"position: relative; padding-bottom: 56.25%; padding-top: 0px; height: 0; overflow: hidden;\">\n\t<iframe style=\"position: absolute; top: 0; left: 0; width: 100%; height: 100%;\" \n        src=\"https://www.youtube.com/embed/J-xUC4WJ2C8\" \n        frameborder=\"0\" crolling=\"no\" frameborder=\"none\" allowfullscreen=\"\">\n    </iframe>\n</div>\n<br><br>\n<h3>Form Mapping</h3>\n<div style=\"position: relative; padding-bottom: 56.25%; padding-top: 0px; height: 0; overflow: hidden;\">\n\t<iframe style=\"position: absolute; top: 0; left: 0; width: 100%; height: 100%;\" \n        src=\"https://www.youtube.com/embed/1tCKnzck2-c\" \n        frameborder=\"0\" crolling=\"no\" frameborder=\"none\" allowfullscreen=\"\">\n    </iframe>\n</div>\n<br><br>\n<h3>Event Based System Integration</h3>\n<div style=\"position: relative; padding-bottom: 56.25%; padding-top: 0px; height: 0; overflow: hidden;\">\n\t<iframe style=\"position: absolute; top: 0; left: 0; width: 100%; height: 100%;\" \n        src=\"https://www.youtube.com/embed/E-tjj20-xxI\" \n        frameborder=\"0\" crolling=\"no\" frameborder=\"none\" allowfullscreen=\"\">\n    </iframe>\n</div>\n<br><br>\n<h3>Message Based System Integration</h3>\n<div style=\"position: relative; padding-bottom: 56.25%; padding-top: 0px; height: 0; overflow: hidden;\">\n\t<iframe style=\"position: absolute; top: 0; left: 0; width: 100%; height: 100%;\" \n        src=\"https://www.youtube.com/embed/bxkB-pkOpTQ\" \n        frameborder=\"0\" crolling=\"no\" frameborder=\"none\" allowfullscreen=\"\">\n    </iframe>\n</div>\n<br><br>\n<h3>Process Animation</h3>\n<div style=\"position: relative; padding-bottom: 56.25%; padding-top: 0px; height: 0; overflow: hidden;\">\n\t<iframe style=\"position: absolute; top: 0; left: 0; width: 100%; height: 100%;\" \n        src=\"https://www.youtube.com/embed/KFjiHCRhxpo\" \n        frameborder=\"0\" crolling=\"no\" frameborder=\"none\" allowfullscreen=\"\">\n    </iframe>\n</div>\n<br><br>\n<h3>Timer Event</h3>\n<div style=\"position: relative; padding-bottom: 56.25%; padding-top: 0px; height: 0; overflow: hidden;\">\n\t<iframe style=\"position: absolute; top: 0; left: 0; width: 100%; height: 100%;\" \n        src=\"https://www.youtube.com/embed/rvUB2aBK4HU\" \n        frameborder=\"0\" crolling=\"no\" frameborder=\"none\" allowfullscreen=\"\">\n    </iframe>\n</div>\n<br><br>\n<h3>Event Handling During Process Execution</h3>\n<div style=\"position: relative; padding-bottom: 56.25%; padding-top: 0px; height: 0; overflow: hidden;\">\n\t<iframe style=\"position: absolute; top: 0; left: 0; width: 100%; height: 100%;\" \n        src=\"https://www.youtube.com/embed/UqqXw6bU7GA\" \n        frameborder=\"0\" crolling=\"no\" frameborder=\"none\" allowfullscreen=\"\">\n    </iframe>\n</div>\n<br><br>\n<h3>AI Agent Form Completion - Form Creation Using uEngine6</h3>\n<div style=\"position: relative; padding-bottom: 56.25%; padding-top: 0px; height: 0; overflow: hidden;\">\n\t<iframe style=\"position: absolute; top: 0; left: 0; width: 100%; height: 100%;\" \n        src=\"https://www.youtube.com/embed/PNNX4_mNeH0\" \n        frameborder=\"0\" crolling=\"no\" frameborder=\"none\" allowfullscreen=\"\">\n    </iframe>\n</div>\n<br><br>\n<h3>Process-GPT System Integration Automation</h3>\n<div style=\"position: relative; padding-bottom: 56.25%; padding-top: 0px; height: 0; overflow: hidden;\">\n\t<iframe style=\"position: absolute; top: 0; left: 0; width: 100%; height: 100%;\" \n        src=\"https://www.youtube.com/embed/pR7AAnxWZ3M\" \n        frameborder=\"0\" crolling=\"no\" frameborder=\"none\" allowfullscreen=\"\">\n    </iframe>\n</div>\n<br><br>\n<h3>Process-GPT Voice Commands</h3>\n<div style=\"position: relative; padding-bottom: 56.25%; padding-top: 0px; height: 0; overflow: hidden;\">\n\t<iframe style=\"position: absolute; top: 0; left: 0; width: 100%; height: 100%;\" \n        src=\"https://www.youtube.com/embed/zLWA2lzAZIg\" \n        frameborder=\"0\" crolling=\"no\" frameborder=\"none\" allowfullscreen=\"\">\n    </iframe>\n</div>\n<br><br>\n<h3>AI-Driven Process Auto-Generation</h3>\n<div style=\"position: relative; padding-bottom: 56.25%; padding-top: 0px; height: 0; overflow: hidden;\">\n\t<iframe style=\"position: absolute; top: 0; left: 0; width: 100%; height: 100%;\" \n        src=\"https://www.youtube.com/embed/DI4vLwijsMs\" \n        frameborder=\"0\" crolling=\"no\" frameborder=\"none\" allowfullscreen=\"\">\n    </iframe>\n</div>\n<br><br>\n<!-- ## 유엔진 아키텍처\n\n### 유엔진 프로세스 모델 정의\n<h3>유엔진 프로세스 모델 정의 1</h3>\n<div style = \"height:350px; object-fit: cover;\">\n<iframe style = \"width:100%; height:100%;\" src=\"https://www.youtube.com/embed/bxkB-pkOpTQ\" title=\"YouTube video player\" frameborder=\"0\" allow=\"accelerometer; autoplay; clipboard-write; encrypted-media; gyroscope; picture-in-picture\" allowfullscreen></iframe>\n</div>\n\n<br>\n\n<h3>유엔진 프로세스 모델 정의 2</h3>\n<div style = \"height:350px; object-fit: cover;\">\n<iframe style = \"width:100%; height:100%;\" src=\"https://www.youtube.com/embed/mGJ8CAnzc6Q\" title=\"YouTube video player\" frameborder=\"0\" allow=\"accelerometer; autoplay; clipboard-write; encrypted-media; gyroscope; picture-in-picture\" allowfullscreen></iframe>\n</div>\n\n<br><br>\n\n### 유엔진 사용자 정의\n<h3>유엔진 사용자 정의 1</h3>\n<div style = \"height:350px; object-fit: cover;\">\n<iframe style = \"width:100%; height:100%;\" src=\"https://www.youtube.com/embed/ricAyobgOWc\" title=\"YouTube video player\" frameborder=\"0\" allow=\"accelerometer; autoplay; clipboard-write; encrypted-media; gyroscope; picture-in-picture\" allowfullscreen></iframe>\n</div>\n\n\n<br>\n\n<h3>유엔진 사용자 정의 2</h3>\n<div style = \"height:350px; object-fit: cover;\">\n<iframe style = \"width:100%; height:100%;\" src=\"https://www.youtube.com/embed/y18BVqzF3HQ\" title=\"YouTube video player\" frameborder=\"0\" allow=\"accelerometer; autoplay; clipboard-write; encrypted-media; gyroscope; picture-in-picture\" allowfullscreen></iframe>\n</div>\n\n<br>\n\n<h3>유엔진 사용자 정의 3</h3>\n<div style = \"height:350px; object-fit: cover;\">\n<iframe style = \"width:100%; height:100%;\" src=\"https://www.youtube.com/embed/4AcukQYQRNY\" title=\"YouTube video player\" frameborder=\"0\" allow=\"accelerometer; autoplay; clipboard-write; encrypted-media; gyroscope; picture-in-picture\" allowfullscreen></iframe>\n</div>\n\n<br><br>\n\n### 엔진 내부 해부\n<h3>엔진 내부 해부 1</h3>\n<div style = \"height:350px; object-fit: cover;\">\n<iframe style = \"width:100%; height:100%;\" src=\"https://www.youtube.com/embed/KmzrYCy275s\" title=\"YouTube video player\" frameborder=\"0\" allow=\"accelerometer; autoplay; clipboard-write; encrypted-media; gyroscope; picture-in-picture\" allowfullscreen></iframe>\n</div>\n\n\n<br>\n\n<h3>엔진 내부 해부 2</h3>\n<div style = \"height:350px; object-fit: cover;\">\n<iframe style = \"width:100%; height:100%;\" src=\"https://www.youtube.com/embed/BIecI-Va3SA\" title=\"YouTube video player\" frameborder=\"0\" allow=\"accelerometer; autoplay; clipboard-write; encrypted-media; gyroscope; picture-in-picture\" allowfullscreen></iframe>\n</div>\n\n<br>\n\n<h3>엔진 내부 해부 3</h3>\n<div style = \"height:350px; object-fit: cover;\">\n<iframe style = \"width:100%; height:100%;\" src=\"https://www.youtube.com/embed/PhssGDmjCWw\" title=\"YouTube video player\" frameborder=\"0\" allow=\"accelerometer; autoplay; clipboard-write; encrypted-media; gyroscope; picture-in-picture\" allowfullscreen></iframe>\n</div>\n\n<br><br>\n\n## 유엔진 개발환경 셋팅\n\n### 디버깅 및 소스 분석\n\n<h3>디버깅 및 소스 분석 1</h3>\n<div style = \"height:350px; object-fit: cover;\">\n<iframe style = \"width:100%; height:100%;\" src=\"https://www.youtube.com/embed/bd2-CG6hSn0\" title=\"YouTube video player\" frameborder=\"0\" allow=\"accelerometer; autoplay; clipboard-write; encrypted-media; gyroscope; picture-in-picture\" allowfullscreen></iframe>\n</div>\n\n\n<br>\n\n<h3>디버깅 및 소스 분석 2</h3>\n<div style = \"height:350px; object-fit: cover;\">\n<iframe style = \"width:100%; height:100%;\" src=\"https://www.youtube.com/embed/D04xN2PuP4I\" title=\"YouTube video player\" frameborder=\"0\" allow=\"accelerometer; autoplay; clipboard-write; encrypted-media; gyroscope; picture-in-picture\" allowfullscreen></iframe>\n</div>\n\n<br><br>\n\n### 이클립스 설정\n\n<h3>이클립스 설정 1</h3>\n<div style = \"height:350px; object-fit: cover;\">\n<iframe style = \"width:100%; height:100%;\" src=\"https://www.youtube.com/embed/3e2YXMBjWBU\" title=\"YouTube video player\" frameborder=\"0\" allow=\"accelerometer; autoplay; clipboard-write; encrypted-media; gyroscope; picture-in-picture\" allowfullscreen></iframe>\n</div>\n\n\n<br>\n\n<h3>이클립스 설정 2</h3>\n<div style = \"height:350px; object-fit: cover;\">\n<iframe style = \"width:100%; height:100%;\" src=\"https://www.youtube.com/embed/CML13YxYBW4\" title=\"YouTube video player\" frameborder=\"0\" allow=\"accelerometer; autoplay; clipboard-write; encrypted-media; gyroscope; picture-in-picture\" allowfullscreen></iframe>\n</div> -->\n","sidebar":"getting-started","next":"","prev":"","headings":[{"depth":1,"value":"Feature Demo Videos","anchor":"#feature-demo-videos"}]},"allMarkdownPage":{"edges":[{"node":{"path":"/process-example/","title":"Loan Management Process"}},{"node":{"path":"/pal-edition/index2/","title":"BPMN PAL 매뉴얼"}},{"node":{"path":"/pal-edition/","title":"PAL Overview and Purpose"}},{"node":{"path":"/pal-edition/process-definition-map/","title":"Process Definition System Diagram Creation Method"}},{"node":{"path":"/getting-started/soa-architecture/","title":"SOA (MSA) 아키텍처 예제"}},{"node":{"path":"/pal-edition/process-definition-edit/","title":"Process Editing"}},{"node":{"path":"/process-example/call-activity/","title":"콜 액티비티(Call Activity)의 활용"}},{"node":{"path":"/process-example/sub-process/","title":"서브 프로세스를 활용한 프로세스 작성"}},{"node":{"path":"/getting-started/soa-architecture-message/","title":"SOA (MSA) 아키텍처 예제 - Message"}},{"node":{"path":"/getting-started/soa-architecture-event/","title":"SOA (MSA) 아키텍처 예제 - Event"}},{"node":{"path":"/getting-started/multiple-instance/","title":"멀티플 인스턴스"}},{"node":{"path":"/getting-started/process-definition/","title":""}},{"node":{"path":"/getting-started/process-workflow/","title":"사람간의 프로세스 Workflow"}},{"node":{"path":"/getting-started/process-monitoring/","title":"프로세스 실행"}},{"node":{"path":"/getting-started/","title":"실행환경 구성"}},{"node":{"path":"/getting-started/modeling-tools/","title":"모델링 툴의 사용법"}},{"node":{"path":"/getting-started/form-mapping/","title":"폼 매핑"}},{"node":{"path":"/getting-started/form-definition/","title":"폼 관리"}},{"node":{"path":"/getting-started/database-table/","title":"테이블 정의"}},{"node":{"path":"/bpm6-intro/","title":"introduction"}},{"node":{"path":"/getting-started/conditional-branch/","title":"조건 분기 처리"}},{"node":{"path":"/bpm6-intro/bpm6-timer/","title":"타이머 이벤트"}},{"node":{"path":"/bpm6-intro/business-process/","title":"BPM and Business Processes"}},{"node":{"path":"/bpm6-intro/example-video/","title":"Feature Demo Videos"}},{"node":{"path":"/bpm6-intro/bpm6-introduce/","title":"소개하기"}},{"node":{"path":"/bpm6-started/","title":"How to Use the Modeling Tool"}},{"node":{"path":"/bpm6-started/script-task/","title":"[Modeling] ScriptTask"}},{"node":{"path":"/bpm6-intro/bpm6-animation/","title":"프로세스 애니메이션"}},{"node":{"path":"/bpm6-started/conditional-branch/","title":"Conditional Branching"}},{"node":{"path":"/bpm6-started/multiple-instance/","title":"Multi-Instance Processing"}},{"node":{"path":"/bpm6-started/form-mapping/","title":"Data Mapping"}},{"node":{"path":"/bpm6-started/bpm6-modeling/","title":"Components"}},{"node":{"path":"/bpm6-started/form-definition/","title":"Form Management"}},{"node":{"path":"/bpm6-deploy-config/","title":"Running"}},{"node":{"path":"/bpm6-started/bpm6-external/","title":"External Service Integration"}},{"node":{"path":"/bpm6-started/bpm6-execution/","title":"Process Execution"}},{"node":{"path":"/bpm6-contact/","title":"License and Contact Information"}},{"node":{"path":"/bpm6-deploy-config/bpm6-system-integration/","title":"uEngine6 BPM 배포 설정"}},{"node":{"path":"/bpm6-deploy-config/uengine3-migration/","title":"uEngine3.x Migration"}},{"node":{"path":"/bpm6-deploy-config/bpm6-account/","title":"Account Management and Access Methods"}},{"node":{"path":"/bpm6-deploy-config/bpm6-deploy/","title":"Deployment"}},{"node":{"path":"/bpm6-api/","title":"API Reference"}},{"node":{"path":"/bpm6-api/bpm6-transaction-listener/","title":"uEngine6 Transaction Listener"}},{"node":{"path":"/bpm6-api/bpm6-message-listener/","title":"Message Listener API"}},{"node":{"path":"/bpm6-admin/bpm6-admin-instance/","title":"인스턴스 관리기능"}},{"node":{"path":"/bpm6-admin/","title":"Administrator Page Features and Overview"}},{"node":{"path":"/bpm6-admin/bpm6-file/","title":"Data Management - Files"}},{"node":{"path":"/bpm6-admin/bpm6-database/","title":"Data Management - Database"}},{"node":{"path":"/bpm-engine/resource-manager/","title":"Resource Manager"}},{"node":{"path":"/bpm-engine/introduction/","title":"기본 소개"}},{"node":{"path":"/bpm-engine/execution/","title":"실행하기"}},{"node":{"path":"/bpm-engine/instance/","title":"Instance"}},{"node":{"path":"/bpm-engine/definition/","title":"Definition"}},{"node":{"path":"/bpm-concept/workflow/","title":"워크플로우"}},{"node":{"path":"/bpm-engine/activity/","title":"Activity"}},{"node":{"path":"/bpm-concept/workflow-management-system/","title":"워크플로우 관리 시스템과 RTE BPM"}},{"node":{"path":"/bpm-concept/open-source/","title":"오픈소스 BPMS uEngine 소개"}},{"node":{"path":"/bpm-concept/facebook/","title":"Facebook group"}},{"node":{"path":"/bpm-concept/business-process/","title":"비즈니스 프로세스와 BPM"}},{"node":{"path":"/bpm-concept/example-video/","title":"Example Video"}},{"node":{"path":"/api-customizing/script-task/","title":"ScriptTask"}},{"node":{"path":"/api-customizing/transaction-listener/","title":"uEngine6 트랜잭션 리스너"}},{"node":{"path":"/api-customizing/new-activity/","title":"새로운 액티비티 타입 만들기"}},{"node":{"path":"/api-customizing/migration/","title":"uEngine3.x 마이그래이션"}},{"node":{"path":"/api-customizing/api-reference/","title":"uEngine6 API Reference"}},{"node":{"path":"/api-customizing/message-listener/","title":"[API] Message Listener API"}},{"node":{"path":"/api-customizing/create-project/","title":"uEngine6 기반 프로젝트 만들기"}},{"node":{"path":"/api-customizing/api-reference-old/","title":"uEngine6 API Reference"}},{"node":{"path":"/api-customizing/external-service/","title":"애플리케이션과 BPM 연동(비동기 방식)"}},{"node":{"path":"/ai-generating/","title":"AI를 활용한 프로세스 생성 기능 소개"}},{"node":{"path":"/api-customizing/bpm-to-service/","title":"BPM에서 외부 서비스 연동 "}},{"node":{"path":"/ai-generating/process-definition/","title":"프로세스 정의 가이드"}},{"node":{"path":"/ai-generating/form-definition/","title":"폼 정의 가이드"}}]}},"context":{}}